MANIFEST.in
README.md
setup.py
pync/TerminalNotifier.py
pync/__init__.py
pync.egg-info/PKG-INFO
pync.egg-info/SOURCES.txt
pync.egg-info/dependency_links.txt
pync.egg-info/requires.txt
pync.egg-info/top_level.txt
pync.egg-info/zip-safe
pync/vendor/terminal-notifier-2.0.0/README.markdown
pync/vendor/terminal-notifier-2.0.0/terminal-notifier.app/Contents/Info.plist
pync/vendor/terminal-notifier-2.0.0/terminal-notifier.app/Contents/PkgInfo
pync/vendor/terminal-notifier-2.0.0/terminal-notifier.app/Contents/MacOS/terminal-notifier
pync/vendor/terminal-notifier-2.0.0/terminal-notifier.app/Contents/Resources/Terminal.icns
pync/vendor/terminal-notifier-2.0.0/terminal-notifier.app/Contents/Resources/en.lproj/Credits.rtf
pync/vendor/terminal-notifier-2.0.0/terminal-notifier.app/Contents/Resources/en.lproj/InfoPlist.strings
pync/vendor/terminal-notifier-2.0.0/terminal-notifier.app/Contents/Resources/en.lproj/MainMenu.nib