Metadata-Version: 1.1
Name: pync
Version: 2.0.3
Summary: Python Wrapper for Mac OS 10.10 Notification Center
Home-page: https://github.com/setem/pync
Author: Vladislav Syabruk
Author-email: sjabrik@gmail.com
License: MIT
Keywords: mac notification center wrapper
Platform: MacOS X
Classifier: Development Status :: 5 - Production/Stable
Classifier: Environment :: Console
Classifier: License :: OSI Approved :: MIT License
Classifier: Programming Language :: Python :: 2.7
Classifier: Programming Language :: Python :: 3.4
Classifier: Programming Language :: Python :: 3.5
Classifier: Programming Language :: Python :: 3.6
Classifier: Environment :: MacOS X
Classifier: Topic :: Terminals
Classifier: Topic :: Utilities
Classifier: Topic :: Software Development :: Libraries :: Python Modules
